testgen/__init__.py
pyinfra_testgen-0.1.1.dist-info/WHEEL
pyinfra_testgen-0.1.1.dist-info/METADATA
pyinfra_testgen-0.1.1.dist-info/RECORD
