Metadata-Version: 2.3
Name: pyinfra-testgen
Version: 0.1.1
Summary: Generate Python unit tests from JSON and YAML files
Requires-Dist: pyyaml==6.*
Requires-Python: >=3.9
